nonebot_plugin_word_bank2-0.2.1.dist-info/METADATA
nonebot_plugin_word_bank2-0.2.1.dist-info/WHEEL
nonebot_plugin_word_bank2-0.2.1.dist-info/entry_points.txt
nonebot_plugin_word_bank2-0.2.1.dist-info/licenses/LICENSE
nonebot_plugin_word_bank2/__init__.py
nonebot_plugin_word_bank2/data_source.py
nonebot_plugin_word_bank2/models.py
nonebot_plugin_word_bank2/util.py
nonebot_plugin_word_bank2/word_entry.py
nonebot_plugin_word_bank2-0.2.1.dist-info/RECORD
