Metadata-Version: 2.4
Name: nonebot-plugin-word-bank2
Version: 0.2.1
Summary: 无数据问答插件
Author-Email: kexue <x@kexue-cloud.cn>
License-Expression: GPL-3.0
Project-URL: homepage, https://github.com/kexue-z/nonebot-plugin-word-bank2
Requires-Python: <4.0,>=3.10
Requires-Dist: httpx>=0.28.1
Requires-Dist: nonebot-adapter-onebot>=2.4.6
Requires-Dist: nonebot-plugin-alconna>=0.54.1
Requires-Dist: nonebot-plugin-localstore>=0.7.3
Requires-Dist: nonebot2>=2.4.0
